.gitignore
.readthedocs.yaml
LICENSE
PyORBIT_GetResults.py
PyORBIT_Results.py
PyORBIT_Run.py
README.md
extra_requirements.txt
fetch_constants.sh
setup.py
starry_requirements.txt
deprecated/batman_transit_subset.py
deprecated/batman_transit_ttv_subset_bkp.py
deprecated/batman_transit_ttv_subset_faster.py
deprecated/batman_transit_ttv_subset_mod.py
deprecated/celerite_matern32.py
deprecated/celerite_matern32_common.py
deprecated/celerite_rotation.py
deprecated/celerite_term.py
deprecated/dynamical_modelling_backup.py
deprecated/gp_quasiperiodic_activity_common.py
deprecated/lightcurve_detrending.py
deprecated/lightcurve_linear_detrending.py
deprecated/lightcurve_poly_detrending.py
deprecated/radial_velocities.py
development/GP_3d.py
development/GP_3d_new.py
development/RML_testing.ipynb
development/RRM_testing.ipynb
development/check_RML.py
development/test_iparam.ipynb
development/test_multi.py
development/test_numpy_dot.py
development/test_tinygp.py
development/gp_test/quasiperiodic_cosine.ipynb
development/gp_test/test_02.ipynb
development/latentQP_decorrelatedSE/compare_GPs.ipynb
development/latentQP_decorrelatedSE/jax_testing.ipynb
development/nautilus/Untitled.ipynb
development/orvara/HD159062_PyORBIT_RVs.yaml
development/orvara/config_HD159062.ini
development/orvara/test_orvara.ipynb
development/orvara/data/HD159062_RV.dat
development/orvara/data/HD159062_RV_PyORBIT.dat
development/orvara/data/HD159062_relAST.txt
development/orvara/data/HGCA_vEDR3.fits
development/orvara/data/gaia/HIP085653.csv
development/orvara/data/hip1/085653.txt
development/orvara/data/hip2/H085653.d
development/photodynamical/script.py
development/photodynamical/simple_photoTRADES-Copy1.ipynb
development/photodynamical/simple_photoTRADES.ipynb
development/photodynamical/.virtual_documents/simple_photoTRADES.ipynb
development/photodynamical/photoTRADES_TOI-1130/example_photoTRADES-Copy1.ipynb
development/photodynamical/photoTRADES_TOI-1130/example_photoTRADES.html
pyorbit_package.egg-info/PKG-INFO
pyorbit_package.egg-info/SOURCES.txt
pyorbit_package.egg-info/dependency_links.txt
pyorbit_package.egg-info/entry_points.txt
pyorbit_package.egg-info/not-zip-safe
pyorbit_package.egg-info/requires.txt
pyorbit_package.egg-info/top_level.txt