Metadata-Version: 2.4
Name: pyorbit-package
Version: 11.0.0
Summary: PyORBIT: a code for exoplanet orbital parameters and stellar activity
Home-page: https://github.com/LucaMalavolta/PyORBIT
Author: Luca Malavolta
Author-email: luca.malavolta@unipd.it
License: MIT
Classifier: Development Status :: 5 - Production/Stable
Classifier: Intended Audience :: Science/Research
Classifier: Topic :: Scientific/Engineering
Classifier: Operating System :: OS Independent
Classifier: Programming Language :: Python :: 3
License-File: LICENSE
Requires-Dist: numpy==1.24.3
Requires-Dist: numba>=0.55.2
Requires-Dist: scipy<1.12.0,>=1.8.1
Requires-Dist: matplotlib<3.8,>=3.5.2
Requires-Dist: astropy>=5.1
Requires-Dist: astroquery>=0.4
Requires-Dist: pyerfa>=2.0
Requires-Dist: argparse
Requires-Dist: emcee>=3.1.2
Requires-Dist: pyyaml
Requires-Dist: h5py
Requires-Dist: tqdm
Requires-Dist: pygtc
Requires-Dist: jaxlib==0.4.31
Requires-Dist: jax==0.4.31
Requires-Dist: tinygp>=0.3.0
Requires-Dist: ordered-set
Requires-Dist: nautilus-sampler
Dynamic: author
Dynamic: author-email
Dynamic: classifier
Dynamic: description
Dynamic: description-content-type
Dynamic: home-page
Dynamic: license
Dynamic: license-file
Dynamic: requires-dist
Dynamic: summary
